vizy/__init__.py
vizy/format_detection.py
vizy-1.4.0.dist-info/METADATA
vizy-1.4.0.dist-info/WHEEL
vizy-1.4.0.dist-info/licenses/LICENSE
vizy-1.4.0.dist-info/RECORD
