Metadata-Version: 2.4
Name: vizy
Version: 1.4.0
Summary: Tiny tensor visualiser: vizy.plot(t) / vizy.save(t)
Project-URL: Repository, https://github.com/anilzeybek/vizy
Project-URL: Issues, https://github.com/anilzeybek/vizy/issues
Author: Anıl Zeybek
License-Expression: MIT
License-File: LICENSE
Keywords: jax,numpy,pytorch,tensor,visualization
Classifier: Development Status :: 4 - Beta
Classifier: Intended Audience :: Developers
Classifier: Intended Audience :: Science/Research
Classifier: License :: OSI Approved :: MIT License
Classifier: Programming Language :: Python :: 3.11
Classifier: Programming Language :: Python :: 3.12
Classifier: Programming Language :: Python :: 3.13
Classifier: Programming Language :: Python :: 3.14
Classifier: Topic :: Scientific/Engineering :: Visualization
Classifier: Topic :: Software Development :: Libraries :: Python Modules
Requires-Python: >=3.11
Requires-Dist: numpy>=1.20.0
Requires-Dist: pillow>=8.0.0
Provides-Extra: jax
Requires-Dist: jax; extra == 'jax'
Provides-Extra: torch
Requires-Dist: torch; extra == 'torch'
